moesifapi/__init__.py
moesifapi/api_helper.py
moesifapi/config_manager.py
moesifapi/configuration.py
moesifapi/decorators.py
moesifapi/governance_manager.py
moesifapi/logger_helper.py
moesifapi/moesif_api_client.py
moesifapi/parse_body.py
moesifapi/update_companies.py
moesifapi/update_users.py
moesifapi/workers.py
moesifapi/app_config/__init__.py
moesifapi/app_config/app_config.py
moesifapi/app_config/regex_config_helper.py
moesifapi/controllers/__init__.py
moesifapi/controllers/api_controller.py
moesifapi/controllers/base_controller.py
moesifapi/controllers/health_controller.py
moesifapi/exceptions/__init__.py
moesifapi/exceptions/api_exception.py
moesifapi/http/__init__.py
moesifapi/http/http_call_back.py
moesifapi/http/http_client.py
moesifapi/http/http_context.py
moesifapi/http/http_method_enum.py
moesifapi/http/http_request.py
moesifapi/http/http_response.py
moesifapi/http/requests_client.py
moesifapi/models/__init__.py
moesifapi/models/base_model.py
moesifapi/models/campaign_model.py
moesifapi/models/company_model.py
moesifapi/models/event_model.py
moesifapi/models/event_request_model.py
moesifapi/models/event_response_model.py
moesifapi/models/status_model.py
moesifapi/models/subscription_model.py
moesifapi/models/user_model.py
moesifapi-1.5.5.dist-info/licenses/LICENSE
tests/controllers/__init__.py
tests/controllers/controller_test_base.py
tests/controllers/test_api_controller.py
moesifapi-1.5.5.dist-info/METADATA
moesifapi-1.5.5.dist-info/WHEEL
moesifapi-1.5.5.dist-info/entry_points.txt
moesifapi-1.5.5.dist-info/top_level.txt
moesifapi-1.5.5.dist-info/RECORD
