Metadata-Version: 2.4
Name: moesifapi
Version: 1.5.5
Summary: Moesif API Lib for Python
Home-page: https://www.moesif.com/docs/api?python#api-libs
Author: Moesif, Inc
Author-email: derric@moesif.com
License: Apache Software License
Keywords: log analysis restful api development debug
Classifier: Development Status :: 4 - Beta
Classifier: Intended Audience :: Developers
Classifier: Topic :: Internet :: Log Analysis
Classifier: Topic :: Software Development :: Debuggers
Classifier: Topic :: Software Development :: Libraries
Classifier: Topic :: Internet :: WWW/HTTP
Classifier: License :: OSI Approved :: Apache Software License
Classifier: Programming Language :: Python :: 2
Classifier: Programming Language :: Python :: 2.6
Classifier: Programming Language :: Python :: 2.7
Classifier: Programming Language :: Python :: 3
Classifier: Programming Language :: Python :: 3.3
Classifier: Programming Language :: Python :: 3.4
Classifier: Programming Language :: Python :: 3.5
License-File: LICENSE
Requires-Dist: requests
Requires-Dist: python-dateutil
Requires-Dist: readerwriterlock>=1.0.9
Requires-Dist: apscheduler>=3.10.4
Provides-Extra: dev
Provides-Extra: test
Requires-Dist: nose; extra == "test"
Dynamic: author
Dynamic: author-email
Dynamic: classifier
Dynamic: description
Dynamic: description-content-type
Dynamic: home-page
Dynamic: keywords
Dynamic: license
Dynamic: license-file
Dynamic: provides-extra
Dynamic: requires-dist
Dynamic: summary
